CHANGELOG.rst
LICENSE.txt
MANIFEST.in
README.md
setup.cfg
setup.py
django_share_me_share_me.egg-info/PKG-INFO
django_share_me_share_me.egg-info/SOURCES.txt
django_share_me_share_me.egg-info/dependency_links.txt
django_share_me_share_me.egg-info/not-zip-safe
django_share_me_share_me.egg-info/requires.txt
django_share_me_share_me.egg-info/top_level.txt
share_me_share_me/__init__.py
share_me_share_me/admin.py
share_me_share_me/models.py
share_me_share_me/urls.py
share_me_share_me/views.py
share_me_share_me/migrations/0001_initial.py
share_me_share_me/migrations/__init__.py
share_me_share_me/scss/_sticky.scss
share_me_share_me/static/share_me_share_me/css/sticky.css
share_me_share_me/static/share_me_share_me/css/sticky.min.css
share_me_share_me/static/share_me_share_me/js/sticky.jqueryplugin.js
share_me_share_me/templatetags/__init__.py
share_me_share_me/templatetags/share_me_share_me_tags.py