Metadata-Version: 1.1
Name: django-share-me-share-me
Version: 1.1
Summary: Model and front end library for choosing and integrating social media share widgets.
Home-page: https://github.com/ninapavlich/django-share-me-share-me
Author: Nina Pavlich
Author-email: nina@ninalp.com
License: BSD
Platform: UNKNOWN
Classifier: Development Status :: 4 - Beta
Classifier: Environment :: Web Environment
Classifier: Framework :: Django
Classifier: Intended Audience :: Developers
Classifier: License :: OSI Approved
Classifier: Operating System :: OS Independent
Classifier: Programming Language :: Python
